otk/__init__.py
otk/_utility.py
otk/abcd.py
otk/agf.py
otk/asbp/__init__.py
otk/asbp/apps.py
otk/asbp/fsq.py
otk/asbp/math.py
otk/asbp/plotting.py
otk/asbp/profiles.py
otk/asbp/sa.py
otk/asbp/sbt.py
otk/asbp/source.py
otk/asbp/test/__init__.py
otk/asbp/test/test_asbp.py
otk/asbp/test/test_asbp_apps.py
otk/asbp/test/test_asbp_source.py
otk/asbp/test/test_fsq.py
otk/asbp/test/test_profiles.py
otk/asbp/test/test_propagation_flat.py
otk/asbp/test/test_propagation_spherical.py
otk/asbp/test/test_sbt.py
otk/asbp/test/test_tracing.py
otk/asbp/tracing.py
otk/asbp/widgets.py
otk/beams.py
otk/bvar.py
otk/designs/README.md
otk/designs/US02084714-1.zmx
otk/designs/US08934179-4.zmx
otk/designs/aspheric_telecentric_lens.zmx
otk/draw2/__init__.py
otk/draw2/base.py
otk/draw2/cairo.py
otk/draw2/draw2_cairo.py
otk/functions.py
otk/h4t.py
otk/htm.py
otk/og.py
otk/otk_cairo.py
otk/otk_gizeh.py
otk/palettes.py
otk/paraxial.py
otk/pbg.py
otk/pov.py
otk/prism.py
otk/properties/agfs/Edmund-Optics-2018.agf
otk/properties/agfs/HOYA20200314_include_obsolete.agf
otk/properties/agfs/NIKON-HIKARI_201911.AGF
otk/properties/agfs/OHARA_200306_CATALOG.AGF
otk/properties/agfs/README.md
otk/properties/agfs/schottzemax-20180601.agf
otk/properties/agfs/sumita-opt-dl-data-20200511235805.agf
otk/properties/rii/doc/Dispersion formulas.docx
otk/properties/rii/doc/Dispersion formulas.pdf
otk/properties/rii/doc/changelog.txt
otk/properties/rii/doc/legalcode.txt
otk/properties/rii/glass/ami/AMTIR-1.yml
otk/properties/rii/glass/ami/AMTIR-2.yml
otk/properties/rii/glass/ami/AMTIR-3.yml
otk/properties/rii/glass/ami/AMTIR-6.yml
otk/properties/rii/glass/barberini/D0082.yml
otk/properties/rii/glass/barberini/D0191.yml
otk/properties/rii/glass/barberini/D0290.yml
otk/properties/rii/glass/barberini/D0391.yml
otk/properties/rii/glass/barberini/D0587.yml
otk/properties/rii/glass/barberini/D0687.yml
otk/properties/rii/glass/barberini/D0785.yml
otk/properties/rii/glass/barberini/D0888.yml
otk-0.1.2.dist-info/entry_points.txt
otk-0.1.2.dist-info/LICENSE
otk-0.1.2.dist-info/WHEEL
otk-0.1.2.dist-info/METADATA
otk-0.1.2.dist-info/RECORD
