Metadata-Version: 2.1
Name: otk
Version: 0.1.2
Summary: Optics Tool Kit
Home-page: https://github.com/draustin/otk
License: MIT
Author: Dane Austin
Author-email: dane_austin@fastmail.com.au
Requires-Python: >=3.7,<4.0
Classifier: License :: OSI Approved :: MIT License
Classifier: Programming Language :: Python :: 3
Classifier: Programming Language :: Python :: 3.7
Classifier: Programming Language :: Python :: 3.8
Requires-Dist: cairocffi (>=1.1.0,<2.0.0)
Requires-Dist: chardet (>=3.0.4,<4.0.0)
Requires-Dist: gizeh (>=0.1.11,<0.2.0)
Requires-Dist: ipython (>=7.14.0,<8.0.0)
Requires-Dist: mathx (>=0.2,<0.3)
Requires-Dist: matplotlib (>=3.2.1,<4.0.0)
Requires-Dist: numba (>=0.49.1,<0.50.0)
Requires-Dist: numpy (>=1.18.4,<2.0.0)
Requires-Dist: opt_einsum (>=3.2.1,<4.0.0)
Requires-Dist: pyfftw (>=0.12.0,<0.13.0)
Requires-Dist: pyopengl (>=3.1.5,<4.0.0)
Requires-Dist: pyqt5 (>=5.12,<6.0)
Requires-Dist: pyqtgraph_extensions (>=0.4.0,<0.5.0)
Requires-Dist: pyyaml (>=5.3.1,<6.0.0)
Project-URL: Repository, https://github.com/draustin/otk
